KLplus/__init__.py
KLplus/__main__.py
KLplus/_version.py
KLplus/klplus.py
KLplus/pyxhook.py
KLplus-0.1.2.dist-info/LICENSE
KLplus-0.1.2.dist-info/METADATA
KLplus-0.1.2.dist-info/WHEEL
KLplus-0.1.2.dist-info/dependency_links.txt
KLplus-0.1.2.dist-info/top_level.txt
KLplus-0.1.2.dist-info/RECORD
