Metadata-Version: 2.1
Name: KLplus
Version: 0.1.2
Summary: Um Keylogger CLI para OS Linux baseado no principio KISS.
Home-page: https://github.com/danbros/KLplus
Author: Dan Barros
Author-email: dpb4fun@gmail.com
License: GNU GPLv2
Platform: Linux
Classifier: Development Status :: 5 - Production/Stable
Classifier: Environment :: Console
Classifier: Intended Audience :: Developers
Classifier: Intended Audience :: End Users/Desktop
Classifier: Natural Language :: Portuguese (Brazilian)
Classifier: Operating System :: POSIX :: Linux
Classifier: Programming Language :: Python :: 3.6
Classifier: Programming Language :: Python :: 3.7
Classifier: Programming Language :: Python :: Implementation :: CPython
Classifier: Topic :: System :: Monitoring
Classifier: Topic :: System :: Logging
Requires-Dist: python-xlib (==0.25)
